appy/__init__.py
appy/__main__.py
appy/assets/__init__.py
appy/assets/meirg-logo.jpg
appy/core/__init__.py
appy/core/app.py
appy/utils/__init__.py
appy/utils/img_ascii.py
appy/utils/message.py
unfor19_appy-1.0.0rc21.dist-info/METADATA
unfor19_appy-1.0.0rc21.dist-info/WHEEL
unfor19_appy-1.0.0rc21.dist-info/entry_points.txt
unfor19_appy-1.0.0rc21.dist-info/top_level.txt
unfor19_appy-1.0.0rc21.dist-info/RECORD
