Metadata-Version: 2.1
Name: unfor19-appy
Version: 1.0.0rc21
Summary: Python project template
Home-page: https://github.com/unfor19/python-project
Author: Meir Gabay
Author-email: unfor19@gmail.com
License: MIT
Download-URL: https://github.com/unfor19/python-project/archive/1.0.0rc21.tar.gz
Project-URL: Documentation, https://github.com/unfor19/python-project/wiki
Keywords: python,project,template
Platform: any
Classifier: Development Status :: 5 - Production/Stable
Classifier: Intended Audience :: Developers
Classifier: Topic :: Software Development :: Build Tools
Classifier: License :: OSI Approved :: MIT License
Classifier: Programming Language :: Python :: 3.6
Classifier: Programming Language :: Python :: 3.7
Classifier: Programming Language :: Python :: 3.8
Classifier: Programming Language :: Python :: 3.9
Classifier: Operating System :: POSIX :: Linux
Classifier: Operating System :: Unix
Classifier: Operating System :: MacOS
Classifier: Operating System :: Microsoft :: Windows
Requires-Python: ~=3.6
Requires-Dist: requests (>=2.24.0)
Requires-Dist: pillow (>=8.0.1)
